Workbook

Sheet Checklist
A1: CHECK-LIST DE FIN DE FORMATION — ANGEL'S GROUP
A2: Stagiaire : | D2: Fonction : | F2: Date : | I2: Formateur :
A3: N° | B3: Module concerné | C3: Sous-module | D3: Acteur | E3: Point à valider | F3: Application / écran | G3: Acquis | H3: Date | I3: Formateur | J3: Observations
A4: 1 | B4: Livraison (Distributions) | C4: Commandes | D4: Responsable commercial | E4: Créer, confirmer et importer une commande | F4: distribution.html > Commandes
A5: 2 | B5: Livraison (Distributions) | C5: Commandes | D5: Responsable commercial | E5: Gérer clients et vendeurs partenaires (fiche, candidature) | F5: distribution.html > Tiers
A6: 3 | B6: Livraison (Distributions) | C6: Commandes | D6: Responsable commercial | E6: Établir facture, reçu, avoir | F6: distribution.html > Documents
A7: 4 | B7: Livraison (Distributions) | C7: Commandes | D7: Client | E7: Programmer une livraison depuis le portail | F7: portail.html
A8: 5 | B8: Livraison (Distributions) | C8: Commandes | D8: Client | E8: Suivre sa livraison et signer la réception | F8: lien.html / signer.html
A9: 6 | B9: Livraison (Distributions) | C9: Stock et préparation | D9: Préparateur | E9: Préparer commande, imprimer étiquettes colis | F9: Commandes > Préparation
A10: 7 | B10: Livraison (Distributions) | C10: Stock et préparation | D10: Préparateur | E10: Réceptionner collectes et retours de colis | F10: Centre de livraison > Collectes / Retours
A11: 8 | B11: Livraison (Distributions) | C11: Stock et préparation | D11: Préparateur | E11: Saisir entrées de stock et inventaire | F11: Produits et stock
A12: 9 | B12: Livraison (Distributions) | C12: Stock et préparation | D12: Responsable commercial | E12: Créer produits, traiter candidatures vendeurs | F12: Produits et stock
A13: 10 | B13: Livraison (Distributions) | C13: Livraison | D13: Superviseur des livraisons | E13: Affecter livreur, planifier collecte, suivre course | F13: Centre de livraison
A14: 11 | B14: Livraison (Distributions) | C14: Livraison | D14: Superviseur des livraisons | E14: Utiliser tour de contrôle et carte en direct | F14: Centre > Tour de contrôle
A15: 12 | B15: Livraison (Distributions) | C15: Livraison | D15: Superviseur des livraisons | E15: Traiter échecs, retours, incidents | F15: Centre > Échecs et retours
... A71: 68 | B71: Transversal (Groupe) | C71: Accueil du groupe | D71: Tous | E71: Changer son mot de passe, respecter règles de sécurité | F71: Profil

Sheet Synthèse
A1: Module concerné | B1: Acteur | C1: Points | D1: Acquis | E1: En cours | F1: Non acquis | G1: % acquis
A2: Livraison (Distributions) | B2: Responsable commercial | C2: =COUNTIFS(Checklist!$B$4:$B$71,$A2,Checklist!$D$4:$D$71,$B2) | D2: =COUNTIFS(Checklist!$B$4:$B$71,$A2,Checklist!$D$4:$D$71,$B2,Checklist!$G$4:$G$71,"Acquis") | E2: =COUNTIFS(Checklist!$B$4:$B$71,$A2,Checklist!$D$4:$D$71,$B2,Checklist!$G$4:$G$71,"En cours") | F2: =COUNTIFS(Checklist!$B$4:$B$71,$A2,Checklist!$D$4:$D$71,$B2,Checklist!$G$4:$G$71,"Non acquis") | G2: =IF(C2=0,0,D2/C2)
A3: Livraison (Distributions) | B3: Client | C3: =COUNTIFS(Checklist!$B$4:$B$71,$A3,Checklist!$D$4:$D$71,$B3) | D3: =COUNTIFS(Checklist!$B$4:$B$71,$A3,Checklist!$D$4:$D$71,$B3,Checklist!$G$4:$G$71,"Acquis") | E3: =COUNTIFS(Checklist!$B$4:$B$71,$A3,Checklist!$D$4:$D$71,$B3,Checklist!$G$4:$G$71,"En cours") | F3: =COUNTIFS(Checklist!$B$4:$B$71,$A3,Checklist!$D$4:$D$71,$B3,Checklist!$G$4:$G$71,"Non acquis") | G3: =IF(C3=0,0,D3/C3)
A4: Livraison (Distributions) | B4: Préparateur | C4: =COUNTIFS(Checklist!$B$4:$B$71,$A4,Checklist!$D$4:$D$71,$B4) | D4: =COUNTIFS(Checklist!$B$4:$B$71,$A4,Checklist!$D$4:$D$71,$B4,Checklist!$G$4:$G$71,"Acquis") | E4: =COUNTIFS(Checklist!$B$4:$B$71,$A4,Checklist!$D$4:$D$71,$B4,Checklist!$G$4:$G$71,"En cours") | F4: =COUNTIFS(Checklist!$B$4:$B$71,$A4,Checklist!$D$4:$D$71,$B4,Checklist!$G$4:$G$71,"Non acquis") | G4: =IF(C4=0,0,D4/C4)
A5: Livraison (Distributions) | B5: Superviseur des livraisons | C5: =COUNTIFS(Checklist!$B$4:$B$71,$A5,Checklist!$D$4:$D$71,$B5) | D5: =COUNTIFS(Checklist!$B$4:$B$71,$A5,Checklist!$D$4:$D$71,$B5,Checklist!$G$4:$G$71,"Acquis") | E5: =COUNTIFS(Checklist!$B$4:$B$71,$A5,Checklist!$D$4:$D$71,$B5,Checklist!$G$4:$G$71,"En cours") | F5: =COUNTIFS(Checklist!$B$4:$B$71,$A5,Checklist!$D$4:$D$71,$B5,Checklist!$G$4:$G$71,"Non acquis") | G5: =IF(C5=0,0,D5/C5)
A6: Livraison (Distributions) | B6: Livreur | C6: =COUNTIFS(Checklist!$B$4:$B$71,$A6,Checklist!$D$4:$D$71,$B6) | D6: =COUNTIFS(Checklist!$B$4:$B$71,$A6,Checklist!$D$4:$D$71,$B6,Checklist!$G$4:$G$71,"Acquis") | E6: =COUNTIFS(Checklist!$B$4:$B$71,$A6,Checklist!$D$4:$D$71,$B6,Checklist!$G$4:$G$71,"En cours") | F6: =COUNTIFS(Checklist!$B$4:$B$71,$A6,Checklist!$D$4:$D$71,$B6,Checklist!$G$4:$G$71,"Non acquis") | G6: =IF(C6=0,0,D6/C6)
A7: Livraison (Distributions) | B7: Vendeur partenaire | C7: =COUNTIFS(Checklist!$B$4:$B$71,$A7,Checklist!$D$4:$D$71,$B7) | D7: =COUNTIFS(Checklist!$B$4:$B$71,$A7,Checklist!$D$4:$D$71,$B7,Checklist!$G$4:$G$71,"Acquis") | E7: =COUNTIFS(Checklist!$B$4:$B$71,$A7,Checklist!$D$4:$D$71,$B7,Checklist!$G$4:$G$71,"En cours") | F7: =COUNTIFS(Checklist!$B$4:$B$71,$A7,Checklist!$D$4:$D$71,$B7,Checklist!$G$4:$G$71,"Non acquis") | G7: =IF(C7=0,0,D7/C7)
A8: Livraison (Distributions) | B8: Caissier | C8: =COUNTIFS(Checklist!$B$4:$B$71,$A8,Checklist!$D$4:$D$71,$B8) | D8: =COUNTIFS(Checklist!$B$4:$B$71,$A8,Checklist!$D$4:$D$71,$B8,Checklist!$G$4:$G$71,"Acquis") | E8: =COUNTIFS(Checklist!$B$4:$B$71,$A8,Checklist!$D$4:$D$71,$B8,Checklist!$G$4:$G$71,"En cours") | F8: =COUNTIFS(Checklist!$B$4:$B$71,$A8,Checklist!$D$4:$D$71,$B8,Checklist!$G$4:$G$71,"Non acquis") | G8: =IF(C8=0,0,D8/C8)
A9: Livraison (Distributions) | B9: Direction générale | C9: =COUNTIFS(Checklist!$B$4:$B$71,$A9,Checklist!$D$4:$D$71,$B9) | D9: =COUNTIFS(Checklist!$B$4:$B$71,$A9,Checklist!$D$4:$D$71,$B9,Checklist!$G$4:$G$71,"Acquis") | E9: =COUNTIFS(Checklist!$B$4:$B$71,$A9,Checklist!$D$4:$D$71,$B9,Checklist!$G$4:$G$71,"En cours") | F9: =COUNTIFS(Checklist!$B$4:$B$71,$A9,Checklist!$D$4:$D$71,$B9,Checklist!$G$4:$G$71,"Non acquis") | G9: =IF(C9=0,0,D9/C9)
A10: Livraison (Distributions) | B10: Administrateur | C10: =COUNTIFS(Checklist!$B$4:$B$71,$A10,Checklist!$D$4:$D$71,$B10) | D10: =COUNTIFS(Checklist!$B$4:$B$71,$A10,Checklist!$D$4:$D$71,$B10,Checklist!$G$4:$G$71,"Acquis") | E10: =COUNTIFS(Checklist!$B$4:$B$71,$A10,Checklist!$D$4:$D$71,$B10,Checklist!$G$4:$G$71,"En cours") | F10: =COUNTIFS(Checklist!$B$4:$B$71,$A10,Checklist!$D$4:$D$71,$B10,Checklist!$G$4:$G$71,"Non acquis") | G10: =IF(C10=0,0,D10/C10)
A11: Gestion de taxi (Transport) | B11: Gestionnaire de flotte | C11: =COUNTIFS(Checklist!$B$4:$B$71,$A11,Checklist!$D$4:$D$71,$B11) | D11: =COUNTIFS(Checklist!$B$4:$B$71,$A11,Checklist!$D$4:$D$71,$B11,Checklist!$G$4:$G$71,"Acquis") | E11: =COUNTIFS(Checklist!$B$4:$B$71,$A11,Checklist!$D$4:$D$71,$B11,Checklist!$G$4:$G$71,"En cours") | F11: =COUNTIFS(Checklist!$B$4:$B$71,$A11,Checklist!$D$4:$D$71,$B11,Checklist!$G$4:$G$71,"Non acquis") | G11: =IF(C11=0,0,D11/C11)
A12: Gestion de taxi (Transport) | B12: Directeur / propriétaire | C12: =COUNTIFS(Checklist!$B$4:$B$71,$A12,Checklist!$D$4:$D$71,$B12) | D12: =COUNTIFS(Checklist!$B$4:$B$71,$A12,Checklist!$D$4:$D$71,$B12,Checklist!$G$4:$G$71,"Acquis") | E12: =COUNTIFS(Checklist!$B$4:$B$71,$A12,Checklist!$D$4:$D$71,$B12,Checklist!$G$4:$G$71,"En cours") | F12: =COUNTIFS(Checklist!$B$4:$B$71,$A12,Checklist!$D$4:$D$71,$B12,Checklist!$G$4:$G$71,"Non acquis") | G12: =IF(C12=0,0,D12/C12)
A13: Gestion de taxi (Transport) | B13: Caissier | C13: =COUNTIFS(Checklist!$B$4:$B$71,$A13,Checklist!$D$4:$D$71,$B13) | D13: =COUNTIFS(Checklist!$B$4:$B$71,$A13,Checklist!$D$4:$D$71,$B13,Checklist!$G$4:$G$71,"Acquis") | E13: =COUNTIFS(Checklist!$B$4:$B$71,$A13,Checklist!$D$4:$D$71,$B13,Checklist!$G$4:$G$71,"En cours") | F13: =COUNTIFS(Checklist!$B$4:$B$71,$A13,Checklist!$D$4:$D$71,$B13,Checklist!$G$4:$G$71,"Non acquis") | G13: =IF(C13=0,0,D13/C13)
... A20: Transversal (Groupe) | B20: Tous | C20: =COUNTIFS(Checklist!$B$4:$B$71,$A20,Checklist!$D$4:$D$71,$B20) | D20: =COUNTIFS(Checklist!$B$4:$B$71,$A20,Checklist!$D$4:$D$71,$B20,Checklist!$G$4:$G$71,"Acquis") | E20: =COUNTIFS(Checklist!$B$4:$B$71,$A20,Checklist!$D$4:$D$71,$B20,Checklist!$G$4:$G$71,"En cours") | F20: =COUNTIFS(Checklist!$B$4:$B$71,$A20,Checklist!$D$4:$D$71,$B20,Checklist!$G$4:$G$71,"Non acquis") | G20: =IF(C20=0,0,D20/C20)
